pipelinr/pipelinr.py
pipelinr/lib/__init__.py
pipelinr/lib/pipelinr.py
pipelinr/static/index.css
pipelinr/static/index.html
pipelinr/static/simulation.html
pipelinr/templates/404.html
pipelinr-1.0.2.dist-info/LICENSE
pipelinr-1.0.2.dist-info/METADATA
pipelinr-1.0.2.dist-info/WHEEL
pipelinr-1.0.2.dist-info/entry_points.txt
pipelinr-1.0.2.dist-info/top_level.txt
pipelinr-1.0.2.dist-info/RECORD
